leopy/__init__.py
leopy/decorators.py
leopy/utils.py
leopy/leoroutine/__init__.py
leopy/leoroutine/api.py
leopy/leoroutine/chan.py
leopy/leoroutine/coroutine.py
leopy/leoroutine/thread_routine.py
leopy666-0.3.0.dist-info/LICENSE
leopy666-0.3.0.dist-info/METADATA
leopy666-0.3.0.dist-info/WHEEL
leopy666-0.3.0.dist-info/top_level.txt
leopy666-0.3.0.dist-info/RECORD
