Metadata-Version: 2.1
Name: leopy666
Version: 0.3.0
Summary: Python tools developed by Leo.
Home-page: UNKNOWN
Author: Tao Xiang
Author-email: xiang.tao@outlook.de
License: UNKNOWN
Platform: UNKNOWN
Classifier: Programming Language :: Python :: 3
Classifier: License :: OSI Approved :: MIT License
License-File: LICENSE
Requires-Dist: psutil
